<?xml version="1.0" encoding="UTF-8" ?>
<!DOCTYPE mapper PUBLIC "-//mybatis.org//DTD Mapper 3.0//EN" "http://mybatis.org/dtd/mybatis-3-mapper.dtd" >
<mapper namespace="com.xunai.dao.UserDetailMapper" >
  <resultMap id="BaseResultMap" type="com.xunai.entity.UserDetail" >
    <!--
      WARNING - @mbggenerated
      This element is automatically generated by MyBatis Generator, do not modify.
    -->
    <id column="user_id" property="userId" jdbcType="INTEGER" />
    <result column="head_img" property="headImg" jdbcType="VARCHAR" />
    <result column="profile" property="profile" jdbcType="VARCHAR" />
    <result column="isVip" property="isvip" jdbcType="INTEGER" />
    <result column="likes" property="likes" jdbcType="VARCHAR" />
  </resultMap>
  <sql id="Base_Column_List" >
    <!--
      WARNING - @mbggenerated
      This element is automatically generated by MyBatis Generator, do not modify.
    -->
    user_id, head_img, profile, isVip, likes
  </sql>
  <select id="selectByPrimaryKey" resultMap="BaseResultMap" parameterType="java.lang.Integer" >
    <!--
      WARNING - @mbggenerated
      This element is automatically generated by MyBatis Generator, do not modify.
    -->
    select 
    <include refid="Base_Column_List" />
    from user_details
    where user_id = #{userId,jdbcType=INTEGER}
  </select>
  <delete id="deleteByPrimaryKey" parameterType="java.lang.Integer" >
    <!--
      WARNING - @mbggenerated
      This element is automatically generated by MyBatis Generator, do not modify.
    -->
    delete from user_details
    where user_id = #{userId,jdbcType=INTEGER}
  </delete>
  <insert id="insert" parameterType="com.xunai.entity.UserDetail" >
    <!--
      WARNING - @mbggenerated
      This element is automatically generated by MyBatis Generator, do not modify.
    -->
    insert into user_details (user_id, head_img, profile, 
      isVip, likes)
    values (#{userId,jdbcType=INTEGER}, #{headImg,jdbcType=VARCHAR}, #{profile,jdbcType=VARCHAR}, 
      #{isvip,jdbcType=INTEGER}, #{likes,jdbcType=VARCHAR})
  </insert>
  <insert id="insertSelective" parameterType="com.xunai.entity.UserDetail" >
    <!--
      WARNING - @mbggenerated
      This element is automatically generated by MyBatis Generator, do not modify.
    -->
    insert into user_details
    <trim prefix="(" suffix=")" suffixOverrides="," >
      <if test="userId != null" >
        user_id,
      </if>
      <if test="headImg != null" >
        head_img,
      </if>
      <if test="profile != null" >
        profile,
      </if>
      <if test="isvip != null" >
        isVip,
      </if>
      <if test="likes != null" >
        likes,
      </if>
    </trim>
    <trim prefix="values (" suffix=")" suffixOverrides="," >
      <if test="userId != null" >
        #{userId,jdbcType=INTEGER},
      </if>
      <if test="headImg != null" >
        #{headImg,jdbcType=VARCHAR},
      </if>
      <if test="profile != null" >
        #{profile,jdbcType=VARCHAR},
      </if>
      <if test="isvip != null" >
        #{isvip,jdbcType=INTEGER},
      </if>
      <if test="likes != null" >
        #{likes,jdbcType=VARCHAR},
      </if>
    </trim>
  </insert>
  <update id="updateByPrimaryKeySelective" parameterType="com.xunai.entity.UserDetail" >
    <!--
      WARNING - @mbggenerated
      This element is automatically generated by MyBatis Generator, do not modify.
    -->
    update user_details
    <set >
      <if test="headImg != null" >
        head_img = #{headImg,jdbcType=VARCHAR},
      </if>
      <if test="profile != null" >
        profile = #{profile,jdbcType=VARCHAR},
      </if>
      <if test="isvip != null" >
        isVip = #{isvip,jdbcType=INTEGER},
      </if>
      <if test="likes != null" >
        likes = #{likes,jdbcType=VARCHAR},
      </if>
    </set>
    where user_id = #{userId,jdbcType=INTEGER}
  </update>
  <update id="updateByPrimaryKey" parameterType="com.xunai.entity.UserDetail" >
    <!--
      WARNING - @mbggenerated
      This element is automatically generated by MyBatis Generator, do not modify.
    -->
    update user_details
    set head_img = #{headImg,jdbcType=VARCHAR},
      profile = #{profile,jdbcType=VARCHAR},
      isVip = #{isvip,jdbcType=INTEGER},
      likes = #{likes,jdbcType=VARCHAR}
    where user_id = #{userId,jdbcType=INTEGER}
  </update>
</mapper>